MANIFEST.in
distribute_setup.py
setup.py
supay.py
Supay.egg-info/PKG-INFO
Supay.egg-info/SOURCES.txt
Supay.egg-info/dependency_links.txt
Supay.egg-info/top_level.txt
tests/test_script.py
tests/test_supay.py