Metadata-Version: 1.0
Name: Supay
Version: 0.0.8
Summary: A daemonizing library for Python.
Home-page: http://code.google.com/p/supay
Author: Alfredo Deza
Author-email: alfredodeza [at] gmail [dot] com
License: MIT
Keywords: daemon daemonize start stop status spawn process processses
Platform: UNKNOWN
